{
  "kind": "collectionType",
  "collectionName": "profiles",
  "info": {
    "singularName": "profile",
    "pluralName": "profiles",
    "displayName": "profile",
    "description": ""
  },
  "options": {
    "draftAndPublish": true
  },
  "pluginOptions": {},
  "attributes": {
    "name": {
      "type": "string"
    },
    "last_name": {
      "type": "string"
    },
    "email": {
      "type": "email"
    },
    "Genda": {
      "type": "enumeration",
      "enum": [
        "Male",
        "Female"
      ]
    }
  }
}
